{
    "result": {
        "city": "Boston, MA",
		"posts": [
            {
                "name": "Belle Isle Seafood",
				"add1": "1 Main St",
				"add2": "",
				"cty": "Winthrop",
				"stt": "MA",
				"zpcd": "02152",
				"phn": "(617) 567-1619",
				"url": "",
				"note": "Belle Isle Seafood is a local seafood, including chowder and lobster rolls, in a spare, industrial space with inlet views. I ordered their fried Seafood Combo which had fried fish, shrimp, scallops, and I think clams along with French fries and cole slaw. No one can eat all the food you get by themselves. I'm glad I had help finishing it off.",
				"eaten": "yes",
				"photo": "kkk",
				"cptn": "lll",
				"photo2": "mmm",
				"cptn2": "nnn",
				"photo3": "ooo",
				"cptn3": "ppp",
				"prc": "qqq",
				"fdtyp": "rrr",
				"twttr": "sss",
				"fcbk": "ttt",
				"hrs": "uuu"
            },
            {
                "name": "Blunch",
				"add1": "59 E Springfield St",
				"add2": "",
				"cty": "Boston",
				"stt": "MA",
				"zpcd": "02118",
				"phn": "(617) 247-8100",
				"url": "http://www.eatblunch.com/",
				"note": "The Blunch breakfast and lunch counter is turning out hearty pressed sandwiches and chocolate chip cookies until late.",
				"eaten": "no",
				"photo": "kkk",
				"cptn": "lll",
				"photo2": "mmm",
				"cptn2": "nnn",
				"photo3": "ooo",
				"cptn3": "ppp",
				"prc": "qqq",
				"fdtyp": "rrr",
				"twttr": "sss",
				"fcbk": "ttt",
				"hrs": "uuu"
            },
            {
                "name": "Bob’s Lobster",
				"add1": "49 Plum Island Turnpike,",
				"add2": "",
				"cty": "Newbury",
				"stt": "MA",
				"zpcd": "01951",
				"phn": "(978) 465-7100",
				"url": "https://boblobster.com/",
				"note": "Bob’s Lobster is a rough-and-ready fish market and seafood shack with river views along with a cozy, laid-back vibe.",
				"eaten": "no",
				"photo": "kkk",
				"cptn": "lll",
				"photo2": "mmm",
				"cptn2": "nnn",
				"photo3": "ooo",
				"cptn3": "ppp",
				"prc": "qqq",
				"fdtyp": "rrr",
				"twttr": "sss",
				"fcbk": "ttt",
				"hrs": "uuu"
            },
            {
                "name": "Cabot’s Ice Cream",
				"add1": "743 Washington St",
				"add2": "",
				"cty": "Newton",
				"stt": "MA",
				"zpcd": "02460",
				"phn": "(617) 964-9200",
				"url": "http://www.cabots.com/",
				"note": "Cabot’s Ice Cream is a family-friendly diner with dozens of ice cream flavors and three square meals in a nostalgic setting. Order the peanut butter fluff boat.",
				"eaten": "no",
				"photo": "kkk",
				"cptn": "lll",
				"photo2": "mmm",
				"cptn2": "nnn",
				"photo3": "ooo",
				"cptn3": "ppp",
				"prc": "qqq",
				"fdtyp": "rrr",
				"twttr": "sss",
				"fcbk": "ttt",
				"hrs": "uuu"
            },
            {
                "name": "Cutty’s",
				"add1": "284 Washington St",
				"add2": "",
				"cty": "Brookline",
				"stt": "MA",
				"zpcd": "02445",
				"phn": "(617) 505-1844",
				"url": "http://www.cuttyfoods.com/",
				"note": "Cutty’s uses locally sourced, and made-in-house ingredients define this busy breakfast-lunch soup and sandwich joint. You need to get one of the pork sandwiches. Cutty's makes home-made pickled fennel for the pork fennel sandwich.",
				"eaten": "no",
				"photo": "kkk",
				"cptn": "lll",
				"photo2": "mmm",
				"cptn2": "nnn",
				"photo3": "ooo",
				"cptn3": "ppp",
				"prc": "qqq",
				"fdtyp": "rrr",
				"twttr": "sss",
				"fcbk": "ttt",
				"hrs": "uuu"
            },
            {
                "name": "Durgin-Park",
				"add1": "340 N Market St",
				"add2": "",
				"cty": "Boston",
				"stt": "MA",
				"zpcd": "02109",
				"phn": "(617) 227-2038",
				"url": "http://arkrestaurants.com/durgin_park/",
				"note": "Durgin-Park is a historic eatery serving hearty portions of classic New England fare and a wide range of craft beers. You should order the prime rib.",
				"eaten": "no",
				"photo": "kkk",
				"cptn": "lll",
				"photo2": "mmm",
				"cptn2": "nnn",
				"photo3": "ooo",
				"cptn3": "ppp",
				"prc": "qqq",
				"fdtyp": "rrr",
				"twttr": "sss",
				"fcbk": "ttt",
				"hrs": "uuu"
            },
            {
                "name": "Little Donkey",
				"add1": "505 Massachusetts Ave",
				"add2": "",
				"cty": "Cambridge",
				"stt": "MA",
				"zpcd": "02139",
				"phn": "(617) 945-1008",
				"url": "http://www.littledonkeybos.com/",
				"note": "Little Donkey is a chef-driven spot with cool vibe serving international small plates, along with craft beers and cocktails.",
				"eaten": "no",
				"photo": "kkk",
				"cptn": "lll",
				"photo2": "mmm",
				"cptn2": "nnn",
				"photo3": "ooo",
				"cptn3": "ppp",
				"prc": "qqq",
				"fdtyp": "rrr",
				"twttr": "sss",
				"fcbk": "ttt",
				"hrs": "uuu"
            },
            {
                "name": "Maria's Pastry Shop",
				"add1": "46 Cross St",
				"add2": "",
				"cty": "Boston",
				"stt": "MA",
				"zpcd": "02113",
				"phn": "(617) 523-1196",
				"url": "http://mariaspastry.com/",
				"note": "Maria's Pastry Shop is an unassuming Italian baker is offering acclaimed sweets such as cannoli, torrone, and marzipan.",
				"eaten": "yes",
				"photo": "kkk",
				"cptn": "lll",
				"photo2": "mmm",
				"cptn2": "nnn",
				"photo3": "ooo",
				"cptn3": "ppp",
				"prc": "qqq",
				"fdtyp": "rrr",
				"twttr": "sss",
				"fcbk": "ttt",
				"hrs": "uuu"
			},
            {
                "name": "Mike's Pastry",
				"add1": "300 Hanover St",
				"add2": "",
				"cty": "Boston",
				"stt": "MA",
				"zpcd": "02113",
				"phn": "(617) 742-3050",
				"url": "https://www.mikespastry.com/",
				"note": "Mike's Pastry is a renowned Italian bake shop is providing cannoli in multiple flavors, gelati, and biscotti since 1946. Mike's has some of the best cannoli I have ever had. On top of that, they are huge. <strong>NOTE</strong>: They have multiple locations.",
				"eaten": "yes",
				"photo": "https://c2.staticflickr.com/6/5482/13977198540_c59a78c96d_n.jpg",
				"cptn": "Chocolate mouse with chocolate chip cannoli and a ricotta cannoli from Mike!s Pastry in Boston's North End.",
				"photo2": "mmm",
				"cptn2": "nnn",
				"photo3": "ooo",
				"cptn3": "ppp",
				"prc": "qqq",
				"fdtyp": "rrr",
				"twttr": "sss",
				"fcbk": "ttt",
				"hrs": "uuu"
            },
            {
                "name": "Salumeria Italiana",
				"add1": "151 Richmond St",
				"add2": "",
				"cty": "Boston",
				"stt": "MA",
				"zpcd": "02109",
				"phn": "(617) 523-8743",
				"url": "https://salumeriaitaliana.com/",
				"note": "Salumeria Italiana is a quaint fixture selling a range of Italian groceries, including meats, cheeses, pasta, and sauces. They supposedly have the best head cheese/Coppa di Testa in the country.",
				"eaten": "no",
				"photo": "kkk",
				"cptn": "lll",
				"photo2": "mmm",
				"cptn2": "nnn",
				"photo3": "ooo",
				"cptn3": "ppp",
				"prc": "qqq",
				"fdtyp": "rrr",
				"twttr": "sss",
				"fcbk": "ttt",
				"hrs": "uuu"
            },
            {
                "name": "Red Lentil Vegetarian and Vegan Restaurant",
				"add1": "600 Mt Auburn St",
				"add2": "",
				"cty": "Watertown",
				"stt": "MA",
				"zpcd": "02472",
				"phn": "(617) 972-9189",
				"url": "http://theredlentil.com/",
				"note": "Red Lentil Vegetarian and Vegan Restaurant is a destination that serves vegetarian and vegan Indian food with seasonal ingredients with gluten-free options, along with wine, and beer.",
				"eaten": "no",
				"photo": "kkk",
				"cptn": "lll",
				"photo2": "mmm",
				"cptn2": "nnn",
				"photo3": "ooo",
				"cptn3": "ppp",
				"prc": "qqq",
				"fdtyp": "rrr",
				"twttr": "sss",
				"fcbk": "ttt",
				"hrs": "uuu"
            },
            {
                "name": "Roxy's Grilled Cheese",
				"add1": "485 Cambridge St",
				"add2": "",
				"cty": "Allston",
				"stt": "MA",
				"zpcd": "02134",
				"phn": "(617) 202-5864",
				"url": "http://www.roxysgrilledcheese.com/",
				"note": "Roxy's Grilled Cheese is a cheery spin-off of a popular food truck with inventive grilled cheese sandwiches, poutine, and burgers. Don't forget to go through walk-in cooler door to the old school pinball arcade. <strong>NOTE</strong>: They have multiple locations.",
				"eaten": "no",
				"photo": "kkk",
				"cptn": "lll",
				"photo2": "mmm",
				"cptn2": "nnn",
				"photo3": "ooo",
				"cptn3": "ppp",
				"prc": "qqq",
				"fdtyp": "rrr",
				"twttr": "sss",
				"fcbk": "ttt",
				"hrs": "uuu"
            },
            {
                "name": "Veggie Galaxy",
				"add1": "450 Massachusetts Ave",
				"add2": "",
				"cty": "Cambridge",
				"stt": "MA",
				"zpcd": "02139",
				"phn": "(617) 497-1513",
				"url": "http://www.veggiegalaxy.com/",
				"note": "Veggie Galaxy is an imaginative twist on an old-school diner specializing in from-scratch vegan and vegetarian options. I ordered the Pearl Street Redhead Omelette (Portobellos, Caramelized Onion, Feta, Roasted Red Pepper Sauce) and don't forget to ask for their home-made hot sauce it's got the perfect amount of heat and spice for flavor.",
				"eaten": "yes",
				"photo": "kkk",
				"cptn": "lll",
				"photo2": "mmm",
				"cptn2": "nnn",
				"photo3": "ooo",
				"cptn3": "ppp",
				"prc": "qqq",
				"fdtyp": "rrr",
				"twttr": "sss",
				"fcbk": "ttt",
				"hrs": "uuu"
            }
        ]
    }
}